{"GlobalPropertiesHash":"3ugvjP5cxEJ51RNRDs/jXuAwj6H2aMIQWCtKVUgjncM=","FingerprintPatternsHash":"gq3WsqcKBUGTSNle7RKKyXRIwh7M8ccEqOqYvIzoM04=","PropertyOverridesHash":"8ZRc1sGeVrPBx4lD717BgRaQekyh78QKV9SKsdt638U=","InputHashes":["I8qZAumfRilBYuFnOtVyE2eOY11l6FbWkmHZOhsN1\u002Bk=","nzBbABB6RL\u002B4j/5DagncPFIyuYpVACI4XoCItLIfr7M=","52RFxXY7cY51NsyBn7dzN5o7ihuxsBeSUUMqfnV2onY="],"CachedAssets":{"I8qZAumfRilBYuFnOtVyE2eOY11l6FbWkmHZOhsN1\u002Bk=":{"Identity":"C:\\Users\\int.uditha\\OneDrive - Creative Software (Pvt) Ltd\\Desktop\\Projects\\microServicePrac\\bookingPlatform\\ProductService\\ProductService.API\\wwwroot\\uploads\\products\\10070\\b5b41344-f119-4276-887d-a3450bbf3232.jpg","SourceId":"ProductService.API","SourceType":"Discovered","ContentRoot":"C:\\Users\\int.uditha\\OneDrive - Creative Software (Pvt) Ltd\\Desktop\\Projects\\microServicePrac\\bookingPlatform\\ProductService\\ProductService.API\\wwwroot\\","BasePath":"_content/ProductService.API","RelativePath":"uploads/products/10070/b5b41344-f119-4276-887d-a3450bbf3232#[.{fingerprint}]?.jpg","AssetKind":"All","AssetMode":"All","AssetRole":"Primary","AssetMergeBehavior":null,"AssetMergeSource":"","RelatedAsset":null,"AssetTraitName":null,"AssetTraitValue":null,"Fingerprint":"iliaxg6nra","Integrity":"pp00FLL3L6dGB3BE6Gg/2R1bKctGEdg2QbbRLzfGhqo=","CopyToOutputDirectory":"Never","CopyToPublishDirectory":"PreserveNewest","OriginalItemSpec":"wwwroot\\uploads\\products\\10070\\b5b41344-f119-4276-887d-a3450bbf3232.jpg","FileLength":238228,"LastWriteTime":"2025-05-31T06:47:53.6539364+00:00"}},"CachedCopyCandidates":{}}